diploma/__init__.py
diploma/_version.py
diploma-1.0.3.data/data/share/jupyter/labextensions/diploma/package.json
diploma-1.0.3.data/data/share/jupyter/labextensions/diploma/static/568.4004b34d000ad6c6a356.js
diploma-1.0.3.data/data/share/jupyter/labextensions/diploma/static/747.5502c25ad31c15dc26c8.js
diploma-1.0.3.data/data/share/jupyter/labextensions/diploma/static/remoteEntry.411f71f48ed704f476ee.js
diploma-1.0.3.data/data/share/jupyter/labextensions/diploma/static/style.js
diploma-1.0.3.data/data/share/jupyter/labextensions/diploma/static/third-party-licenses.json
diploma-1.0.3.data/data/share/jupyter/labextensions/diploma/install.json
diploma-1.0.3.dist-info/METADATA
diploma-1.0.3.dist-info/WHEEL
diploma-1.0.3.dist-info/licenses/LICENSE
diploma-1.0.3.dist-info/RECORD
