Metadata-Version: 2.1
Name: diploma
Version: 1.0.3
Summary: A JupyterLab extension.
Project-URL: Homepage, https://github.com/FMyb/diplomaext
Project-URL: Bug Tracker, https://github.com/FMyb/diplomaext/issues
Project-URL: Repository, https://github.com/FMyb/diplomaext.git
Author-email: FMyb <neznayu.ucoz.org@gmail.com>
License: BSD 3-Clause License
License-File: LICENSE
Classifier: Framework :: Jupyter
Classifier: Framework :: Jupyter :: JupyterLab
Classifier: Framework :: Jupyter :: JupyterLab :: 3
Classifier: Framework :: Jupyter :: JupyterLab :: Extensions
Classifier: Framework :: Jupyter :: JupyterLab :: Extensions :: Prebuilt
Classifier: License :: OSI Approved :: BSD License
Classifier: Programming Language :: Python
Classifier: Programming Language :: Python :: 3
Classifier: Programming Language :: Python :: 3.7
Classifier: Programming Language :: Python :: 3.8
Classifier: Programming Language :: Python :: 3.9
Classifier: Programming Language :: Python :: 3.10
Classifier: Programming Language :: Python :: 3.11
Requires-Python: >=3.7
